README.md
lumapps/__init__.py
lumapps/api/__init__.py
lumapps/api/base_client.py
lumapps/api/client.py
lumapps/api/conf.py
lumapps/api/decorators.py
lumapps/api/errors.py
lumapps/api/helpers/__init__.py
lumapps/api/helpers/medias.py
lumapps/api/helpers/widgets.py
lumapps/api/lumapps_jwt.py
lumapps/api/utils.py
lumapps/latest/__init__.py
lumapps/latest/api/__init__.py
lumapps/latest/api/article.py
lumapps/latest/api/exceptions.py
lumapps/latest/api/swagger/__init__.py
lumapps/latest/api/swagger/contribution_v1/__init__.py
lumapps/latest/api/swagger/contribution_v1/gateway.py
lumapps/latest/api/swagger/contribution_v1/models/__init__.py
lumapps/latest/api/swagger/contribution_v1/models/all_of_i18n_string_lang.py
lumapps/latest/api/swagger/contribution_v1/models/article.py
lumapps/latest/api/swagger/contribution_v1/models/article_preview.py
lumapps/latest/api/swagger/contribution_v1/models/article_share.py
lumapps/latest/api/swagger/contribution_v1/models/article_with_layout.py
lumapps/latest/api/swagger/contribution_v1/models/attached_link.py
lumapps/latest/api/swagger/contribution_v1/models/base_block.py
lumapps/latest/api/swagger/contribution_v1/models/block_cascade.py
lumapps/latest/api/swagger/contribution_v1/models/block_client_computed.py
lumapps/latest/api/swagger/contribution_v1/models/block_community_preview.py
lumapps/latest/api/swagger/contribution_v1/models/block_directory_entry.py
lumapps/latest/api/swagger/contribution_v1/models/block_event_metadata.py
lumapps/latest/api/swagger/contribution_v1/models/block_featured_image.py
lumapps/latest/api/swagger/contribution_v1/models/block_generic_container.py
lumapps/latest/api/swagger/contribution_v1/models/block_generic_resource.py
lumapps/latest/api/swagger/contribution_v1/models/block_grid.py
lumapps/latest/api/swagger/contribution_v1/models/block_html.py
lumapps/latest/api/swagger/contribution_v1/models/block_image.py
lumapps/latest/api/swagger/contribution_v1/models/block_inappropriate.py
lumapps_sdk-2.0.3.dist-info/LICENSE.md
lumapps_sdk-2.0.3.dist-info/METADATA
lumapps_sdk-2.0.3.dist-info/WHEEL
lumapps_sdk-2.0.3.dist-info/entry_points.txt
lumapps_sdk-2.0.3.dist-info/RECORD
