Metadata-Version: 2.1
Name: lumapps-sdk
Version: 2.0.3
Summary: 
Home-page: https://github.com/lumapps/lumapps-sdk
License: MIT
Keywords: lumapps-sdk,sdk,python
Author: Aurélien Dentan
Author-email: aurelien@lumapps.com
Requires-Python: >=3.8,<4.0
Classifier: License :: OSI Approved :: MIT License
Classifier: Programming Language :: Python :: 3
Classifier: Programming Language :: Python :: 3.8
Classifier: Programming Language :: Python :: 3.9
Classifier: Programming Language :: Python :: 3.10
Classifier: Programming Language :: Python :: 3.11
Classifier: Programming Language :: Python :: 3.12
Classifier: Programming Language :: Python :: 3.13
Requires-Dist: Authlib (<=0.15.3)
Requires-Dist: PyJWT (>=2.1.0,<3.0.0)
Requires-Dist: httpx (>=0.23,<0.24)
Requires-Dist: pre-commit (>=2.13.0,<3.0.0)
Requires-Dist: python-slugify (>=4.0.1,<5.0.0)
Requires-Dist: requests-oauthlib (>=1.3.0,<2.0.0)
Project-URL: Repository, https://github.com/lumapps/lumapps-sdk
